yambs/__init__.py
yambs/__main__.py
yambs/app.py
yambs/dev_requirements.txt
yambs/entry.py
yambs/paths.py
yambs/py.typed
yambs/requirements.txt
yambs/schemas.py
yambs/aggregation/__init__.py
yambs/commands/__init__.py
yambs/commands/all.py
yambs/commands/common.py
yambs/commands/compile_config.py
yambs/commands/dist.py
yambs/commands/download.py
yambs/commands/gen.py
yambs/commands/native.py
yambs/commands/native_manifest.py
yambs/commands/uf2conv.py
yambs/config/__init__.py
yambs/config/board.py
yambs/config/common.py
yambs/config/native.py
yambs/data/native.yaml
yambs/data/uf2families.json
yambs/data/yambs.yaml
yambs/data/includes/chips.yaml
yambs/data/includes/common.yaml
yambs/data/includes/infineon.yaml
yambs/data/includes/microchip.yaml
yambs/data/includes/wasm.yaml
yambs/data/schemas/Architecture.yaml
yambs/data/schemas/Board.yaml
yambs/data/schemas/Chip.yaml
yambs/data/schemas/CommonConfig.yaml
yambs/data/schemas/Config.yaml
yambs/data/schemas/Dependency.yaml
yambs/data/schemas/Github.yaml
yambs/data/schemas/Native.yaml
yambs/data/schemas/Project.yaml
yambs/data/schemas/Toolchain.yaml
yambs/data/schemas/Variant.yaml
yambs/data/schemas/config_common.yaml
yambs/data/schemas/entry_common.yaml
yambs/data/schemas/toolchain_common.yaml
yambs/data/templates/all.ninja.j2
yambs/data/templates/architecture.ninja.j2
yambs/data/templates/board.ninja.j2
yambs/data/templates/build.ninja.j2
yambs/data/templates/chip.ld.j2
yambs/data/templates/chip.ninja.j2
yambs/data/templates/compile_commands.ninja.j2
yambs/data/templates/native_all.ninja.j2
yambs/data/templates/native_build.ninja.j2
yambs/data/templates/native_rules.ninja.j2
yambs/data/templates/regenerate.ninja.j2
yambs/data/templates/rules.ninja.j2
yambs/data/templates/toolchain.ninja.j2
yambs/data/templates/variant.ninja.j2
yambs/dependency/__init__.py
yambs/dependency/config.py
yambs/dependency/github.py
yambs/dependency/manager.py
yambs/dependency/state.py
yambs/dependency/handlers/__init__.py
yambs-3.1.3.dist-info/licenses/LICENSE
yambs-3.1.3.dist-info/METADATA
yambs-3.1.3.dist-info/WHEEL
yambs-3.1.3.dist-info/entry_points.txt
yambs-3.1.3.dist-info/top_level.txt
yambs-3.1.3.dist-info/RECORD
